{
  "project_info": {
    "project_number": "979603481142",
    "project_id": "tracker360-fyp",
    "storage_bucket": "tracker360-fyp.appspot.com"
  },
  "client": [
    {
      "client_info": {
        "mobilesdk_app_id": "1:979603481142:android:6717f3ecccc60fcae26e97",
        "android_client_info": {
          "package_name": "com.example.tracker360"
        }
      },
      "oauth_client": [
        {
          "client_id": "979603481142-811j0ltdpivsegnkiage0qiubhu43ng7.apps.googleusercontent.com",
          "client_type": 3
        }
      ],
      "api_key": [
        {
          "current_key": "AIzaSyC5SnycIzWB06tBgG3k5quZCg5ldBL1KwM"
        }
      ],
      "services": {
        "appinvite_service": {
          "other_platform_oauth_client": [
            {
              "client_id": "979603481142-811j0ltdpivsegnkiage0qiubhu43ng7.apps.googleusercontent.com",
              "client_type": 3
            }
          ]
        }
      }
    }
  ],
  "configuration_version": "1"
}